{
    "0": 119,
    "1": 141,
    "2": 157,
    "3": 179,
    "4": 206,
    "5": 224,
    "6": 228,
    "7": 228,
    "8": 228,
    "9": 228,
    "10": 228,
    "11": 228,
    "12": 228,
    "13": 228,
    "14": 228,
    "15": 229,
    "16": 229,
    "17": 229,
    "18": 229,
    "19": 229,
    "20": 229,
    "21": 229,
    "22": 229,
    "23": 229,
    "24": 229,
    "25": 231,
    "26": 231,
    "27": 231,
    "28": 231,
    "29": 231,
    "30": 231,
    "31": 235,
    "32": 235,
    "33": 235,
    "34": 235,
    "35": 235,
    "36": 235,
    "37": 235,
    "38": 236,
    "39": 236,
    "40": 236,
    "41": 236,
    "42": 236,
    "43": 236,
    "44": 236,
    "45": 236,
    "46": 236,
    "47": 236,
    "48": 236,
    "49": 236,
    "50": 236,
    "51": 236,
    "52": 236,
    "53": 236,
    "54": 236,
    "55": 236,
    "56": 236,
    "57": 236,
    "58": 236
}